ldaptor/__init__.py
ldaptor/_encoder.py
ldaptor/attributeset.py
ldaptor/checkers.py
ldaptor/config.py
ldaptor/delta.py
ldaptor/dns.py
ldaptor/entry.py
ldaptor/entryhelpers.py
ldaptor/generate_password.py
ldaptor/inmemory.py
ldaptor/interfaces.py
ldaptor/ldapfilter.py
ldaptor/ldiftree.py
ldaptor/numberalloc.py
ldaptor/schema.py
ldaptor/testutil.py
ldaptor/usage.py
ldaptor/protocols/__init__.py
ldaptor/protocols/pureber.py
ldaptor/protocols/pureldap.py
ldaptor/protocols/ldap/__init__.py
ldaptor/protocols/ldap/distinguishedname.py
ldaptor/protocols/ldap/fetchschema.py
ldaptor/protocols/ldap/ldapclient.py
ldaptor/protocols/ldap/ldapconnector.py
ldaptor/protocols/ldap/ldaperrors.py
ldaptor/protocols/ldap/ldapserver.py
ldaptor/protocols/ldap/ldapsyntax.py
ldaptor/protocols/ldap/ldif.py
ldaptor/protocols/ldap/ldifdelta.py
ldaptor/protocols/ldap/ldifprotocol.py
ldaptor/protocols/ldap/merger.py
ldaptor/protocols/ldap/proxy.py
ldaptor/protocols/ldap/proxybase.py
ldaptor/protocols/ldap/svcbindproxy.py
ldaptor/protocols/ldap/autofill/__init__.py
ldaptor/protocols/ldap/autofill/posixAccount.py
ldaptor/protocols/ldap/autofill/sambaAccount.py
ldaptor/protocols/ldap/autofill/sambaSamAccount.py
ldaptor/samba/__init__.py
ldaptor/samba/smbpassword.py
ldaptor/test/__init__.py
ldaptor/test/test_attributeset.py
ldaptor/test/test_autofill.py
ldaptor/test/test_autofill_posix.py
ldaptor/test/test_autofill_samba.py
ldaptor/test/test_config.py
ldaptor/test/test_connector.py
ldaptor/test/test_delta.py
ldaptor/test/test_distinguishedname.py
ldaptor/test/test_dns.py
ldaptor/test/test_encoder.py
ldaptor/test/test_entry.py
ldaptor/test/test_examples.py
ldaptor/test/test_fetchschema.py
ldaptor/test/test_inmemory.py
ldaptor/test/test_ldapclient.py
ldaptor/test/test_ldaperrors.py
ldaptor/test/test_ldapfilter.py
ldaptor/test/test_ldapsyntax.py
ldaptor/test/test_ldif.py
ldaptor/test/test_ldifdelta.py
ldaptor/test/test_ldifprotocol.py
ldaptor/test/test_ldiftree.py
ldaptor/test/test_match.py
ldaptor-20.1.1.dist-info/LICENSE
ldaptor-20.1.1.dist-info/METADATA
ldaptor-20.1.1.dist-info/WHEEL
ldaptor-20.1.1.dist-info/top_level.txt
ldaptor-20.1.1.dist-info/RECORD
