Metadata-Version: 2.1
Name: ldaptor
Version: 20.1.1
Summary: A Pure-Python Twisted library for LDAP
Home-page: https://github.com/twisted/ldaptor
Author: Tommi Virtanen
Author-email: tv@eagain.net
Maintainer: Bret Curtis
Maintainer-email: psi29a@gmail.com
License: MIT
Platform: UNKNOWN
Classifier: Intended Audience :: Developers
Classifier: License :: OSI Approved :: MIT License
Classifier: Operating System :: OS Independent
Classifier: Development Status :: 5 - Production/Stable
Classifier: Framework :: Twisted
Classifier: Programming Language :: Python
Classifier: Programming Language :: Python :: 3
Classifier: Programming Language :: Python :: 3.5
Classifier: Programming Language :: Python :: 3.6
Classifier: Programming Language :: Python :: 3.7
Classifier: Programming Language :: Python :: 3.8
Classifier: Topic :: Software Development :: Libraries :: Python Modules
Classifier: Topic :: System :: Systems Administration :: Authentication/Directory :: LDAP
Requires-Python: ~=3.5
Provides-Extra: docs
